AUTHORS.rst
CONTRIBUTING.rst
HISTORY.rst
LICENSE
MANIFEST.in
README.rst
setup.cfg
setup.py
CCC.egg-info/PKG-INFO
CCC.egg-info/SOURCES.txt
CCC.egg-info/dependency_links.txt
CCC.egg-info/not-zip-safe
CCC.egg-info/requires.txt
CCC.egg-info/top_level.txt
ccc/__init__.py
ccc/apps.py
ccc/commonregex.py
ccc/constants.py
ccc/mixin.py
ccc/models.py
ccc/urls.py
ccc/views.py
ccc/api/__init__.py
ccc/api/helpers.py
ccc/api/phones/__init__.py
ccc/api/phones/admin.py
ccc/api/phones/models.py
ccc/api/phones/serializers.py
ccc/api/phones/urls.py
ccc/api/phones/views.py
ccc/api/phones/migrations/0001_initial.py
ccc/api/phones/migrations/__init__.py
ccc/beacons/__init__.py
ccc/beacons/admin.py
ccc/beacons/api.py
ccc/beacons/apps.py
ccc/beacons/models.py
ccc/beacons/serializers.py
ccc/beacons/urls.py
ccc/beacons/views.py
ccc/beacons/migrations/0001_initial.py
ccc/beacons/migrations/__init__.py
ccc/billing/__init__.py
ccc/billing/admin.py
ccc/billing/apps.py
ccc/billing/models.py
ccc/billing/urls.py
ccc/billing/utils.py
ccc/billing/views.py
ccc/billing/migrations/0001_initial.py
ccc/billing/migrations/0002_auto_20190104_0124.py
ccc/billing/migrations/0003_auto_20190105_1023.py
ccc/billing/migrations/__init__.py
ccc/campaigns/__init__.py
ccc/campaigns/admin.py
ccc/campaigns/app_views.py
ccc/campaigns/apps.py
ccc/campaigns/cloud_tasks.py
ccc/campaigns/constant.py
ccc/campaigns/constants.py
ccc/campaigns/exceptions.py
ccc/campaigns/forms.py
ccc/campaigns/models.py
ccc/campaigns/serializers.py
ccc/campaigns/signals.py
ccc/campaigns/urls.py
ccc/campaigns/migrations/0001_initial.py
ccc/campaigns/migrations/0002_auto_20180818_0715.py
ccc/campaigns/migrations/0003_auto_20180926_1917.py
ccc/campaigns/migrations/0004_auto_20181013_0755.py
ccc/campaigns/migrations/0005_emailcampaign_email_type.py
ccc/campaigns/migrations/0006_emailcampaign_premium_template.py
ccc/campaigns/migrations/0007_auto_20181102_1801.py
ccc/campaigns/migrations/0008_auto_20181107_1507.py
ccc/campaigns/migrations/0009_auto_20181109_0841.py
ccc/campaigns/migrations/0010_auto_20181112_1343.py
ccc/campaigns/migrations/0011_auto_20181122_1128.py
