Metadata-Version: 1.1
Name: CCC
Version: 2.0.1
Summary: Cloud Custom Connections
Home-page: https://github.com/CloudPR/CCC
Author: Cloud Custom Solutions Team
Author-email: team@cloudcustomsolutions.com
License: UNKNOWN
Keywords: CCC
Platform: UNKNOWN
Classifier: Development Status :: 3 - Alpha
Classifier: Framework :: Django :: 2.0
Classifier: Intended Audience :: Developers
Classifier: License :: OSI Approved :: BSD License
Classifier: Natural Language :: English
Classifier: Programming Language :: Python :: 3
Classifier: Programming Language :: Python :: 3.4
Classifier: Programming Language :: Python :: 3.5
Classifier: Programming Language :: Python :: 3.6
